h2o_drive/__init__.py
h2o_drive/__main__.py
h2o_drive/client.py
h2o_drive/connection.py
h2o_drive/core.py
h2o_drive/prefixes.py
h2o_drive/sts.py
h2o_drive-4.1.0.dist-info/METADATA
h2o_drive-4.1.0.dist-info/WHEEL
h2o_drive-4.1.0.dist-info/entry_points.txt
h2o_drive-4.1.0.dist-info/RECORD
