Metadata-Version: 2.1
Name: h2o-drive
Version: 4.1.0
Summary: H2O Drive Python Client
Author: H2O.ai
Author-email: support@h2o.ai
Requires-Python: >=3.8,<4.0
Classifier: Intended Audience :: Developers
Classifier: Operating System :: OS Independent
Classifier: Programming Language :: Python :: 3
Classifier: Programming Language :: Python :: 3.8
Classifier: Programming Language :: Python :: 3.9
Classifier: Programming Language :: Python :: 3.10
Classifier: Programming Language :: Python :: 3.11
Classifier: Programming Language :: Python :: 3.12
Classifier: Topic :: Internet
Classifier: Topic :: Scientific/Engineering :: Artificial Intelligence
Requires-Dist: aioboto3 (>=9.3.1)
Requires-Dist: aiobotocore (>=2)
Requires-Dist: botocore (>=1,<1.36.0)
Requires-Dist: click (>=8.1.7)
Requires-Dist: h2o-authn[discovery] (>=2.1.0)
Requires-Dist: h2o-cloud-discovery (>=2.1.0)
